gb_distribution/Binomialdistribution.py
gb_distribution/Gaussiandistribution.py
gb_distribution/Generaldistribution.py
gb_distribution/__init__.py
gb_distribution-1.2.dist-info/METADATA
gb_distribution-1.2.dist-info/WHEEL
gb_distribution-1.2.dist-info/top_level.txt
gb_distribution-1.2.dist-info/RECORD
