Metadata-Version: 2.1
Name: gb-distribution
Version: 1.2
Summary: Gaussian and Binomial distribution
Home-page: UNKNOWN
Author: Dhruva Suman
Author-email: technical.insight@gmail.com
License: UNKNOWN
Platform: UNKNOWN
